{
  "headers": [
    {
      "id": 0,
      "name": "SKU",
      "altNames": ["Stock Keeping Unit", "Product Number"]
    },
    {
      "id": 1,
      "name": "Category",
      "altNames": ["Type", "bracket", "class", "classification", "group"]
    },
    {
      "id": 2,
      "name": "Size",
      "altNames": []
    },
    {
      "id": 3,
      "name": "Gender",
      "altNames": [
        "Sex",
        "M/F"
      ]
    },
    {
      "id": 4,
      "name": "Description",
      "altNames": [
        "About"
      ]
    },
    {
      "id": 5,
      "name": "Materials",
      "altNames": [
        "Mats"
      ]
    },
    {
      "id": 6,
      "name": "MSRP",
      "altNames": ["Price"]
    },
    {
      "id": 7,
      "name": "Active_Date",
      "altNames": []
    },
    {
      "id": 8,
      "name": "Sunset_Date",
      "altNames": []
    }
  ],
  "userdata": [
   
  ]
}